borgo.py
borgo-0.0.7.dist-info/LICENSE
borgo-0.0.7.dist-info/METADATA
borgo-0.0.7.dist-info/WHEEL
borgo-0.0.7.dist-info/top_level.txt
borgo-0.0.7.dist-info/RECORD
