Metadata-Version: 2.1
Name: borgo
Version: 0.0.7
Summary: Library for sending requests to the Borgo app.
Home-page: UNKNOWN
Author: Team Borgo
License: UNKNOWN
Platform: UNKNOWN
Classifier: Programming Language :: Python :: 3
Classifier: License :: OSI Approved :: BSD License
Classifier: Operating System :: OS Independent
Requires-Python: >=3.6
Requires-Dist: python-socketio
Requires-Dist: python-socketio[client]
